<annotation><filename>pos_756.jpg</filename><object><name>helmet</name><position1>0.17935871743486975</position1><position2>0.1751497005988024</position2><position3>0.3587174348697395</position3><position4>0.3383233532934132</position4></object><object><name>helmet</name><position1>0.503006012024048</position1><position2>0.23203592814371257</position2><position3>0.27655310621242485</position3><position4>0.218562874251497</position4></object><object><name>helmet</name><position1>0.718436873747495</position1><position2>0.15568862275449102</position2><position3>0.23446893787575152</position3><position4>0.20958083832335328</position4></object><object><name>helmet</name><position1>0.905811623246493</position1><position2>0.4805389221556886</position2><position3>0.1843687374749499</position3><position4>0.5299401197604791</position4></object></annotation>