<annotation><filename>pos_822.jpg</filename><object><name>helmet</name><position1>0.232</position1><position2>0.2473404255319149</position2><position3>0.204</position3><position4>0.19148936170212766</position4></object><object><name>helmet</name><position1>0.521</position1><position2>0.32845744680851063</position2><position3>0.182</position3><position4>0.1675531914893617</position4></object><object><name>helmet</name><position1>0.744</position1><position2>0.3045212765957447</position2><position3>0.216</position3><position4>0.22074468085106383</position4></object></annotation>