<annotation><filename>pos_378.jpg</filename><object><name>helmet</name><position1>0.8775</position1><position2>0.354</position2><position3>0.23</position3><position4>0.636</position4></object><object><name>helmet</name><position1>0.725</position1><position2>0.458</position2><position3>0.235</position3><position4>0.676</position4></object><object><name>helmet</name><position1>0.51</position1><position2>0.592</position2><position3>0.255</position3><position4>0.744</position4></object><object><name>helmet</name><position1>0.305</position1><position2>0.452</position2><position3>0.27</position3><position4>0.696</position4></object><object><name>helmet</name><position1>0.13375</position1><position2>0.35</position2><position3>0.2575</position3><position4>0.652</position4></object></annotation>