<annotation><filename>pos_1757.jpg</filename><object><name>helmet</name><position1>0.42890625</position1><position2>0.37222222222222223</position2><position3>0.03125</position3><position4>0.05555555555555555</position4></object><object><name>helmet</name><position1>0.6140625</position1><position2>0.10486111111111111</position2><position3>0.059375</position3><position4>0.07083333333333333</position4></object><object><name>west</name><position1>0.67109375</position1><position2>0.20347222222222222</position2><position3>0.1234375</position3><position4>0.16527777777777777</position4></object></annotation>