<annotation><filename>pos_1775.jpg</filename><object><name>helmet</name><position1>0.456640625</position1><position2>0.19166666666666668</position2><position3>0.31953125</position3><position4>0.38333333333333336</position4></object><object><name>west</name><position1>0.451171875</position1><position2>0.8284722222222223</position2><position3>0.65703125</position3><position4>0.3375</position4></object><object><name>helmet</name><position1>0.96640625</position1><position2>0.46458333333333335</position2><position3>0.0640625</position3><position4>0.24583333333333332</position4></object></annotation>